openapi_generator_cli/__init__.py
openapi_generator_cli/openapi-generator.jar
pyopenapigenerator-7.8.0.dist-info/METADATA
pyopenapigenerator-7.8.0.dist-info/WHEEL
pyopenapigenerator-7.8.0.dist-info/entry_points.txt
pyopenapigenerator-7.8.0.dist-info/top_level.txt
pyopenapigenerator-7.8.0.dist-info/RECORD
